flask_mixpanel/__init__.py
flask_mixpanel/core.py
flask_mixpanel-0.2.0.dist-info/LICENSE
flask_mixpanel-0.2.0.dist-info/METADATA
flask_mixpanel-0.2.0.dist-info/WHEEL
flask_mixpanel-0.2.0.dist-info/top_level.txt
flask_mixpanel-0.2.0.dist-info/RECORD
